{
  "version": "0.3.14-fixed",
  "steps": [
    {
      "tag": "CreateModel",
      "model": "Restaurant"
    },
    {
      "tag": "CreateField",
      "model": "Restaurant",
      "field": "id",
      "type": "Int",
      "arity": "Required"
    },
    {
      "tag": "CreateDirective",
      "location": {
        "path": {
          "tag": "Field",
          "model": "Restaurant",
          "field": "id"
        },
        "directive": "id"
      }
    },
    {
      "tag": "CreateDirective",
      "location": {
        "path": {
          "tag": "Field",
          "model": "Restaurant",
          "field": "id"
        },
        "directive": "default"
      }
    },
    {
      "tag": "CreateArgument",
      "location": {
        "tag": "Directive",
        "path": {
          "tag": "Field",
          "model": "Restaurant",
          "field": "id"
        },
        "directive": "default"
      },
      "argument": "",
      "value": "autoincrement()"
    },
    {
      "tag": "CreateField",
      "model": "Restaurant",
      "field": "name",
      "type": "String",
      "arity": "Optional"
    },
    {
      "tag": "CreateField",
      "model": "Restaurant",
      "field": "description",
      "type": "String",
      "arity": "Optional"
    },
    {
      "tag": "CreateField",
      "model": "Restaurant",
      "field": "isActive",
      "type": "Boolean",
      "arity": "Optional"
    }
  ]
}