{
  "version": "0.3.14-fixed",
  "steps": [
    {
      "tag": "CreateModel",
      "model": "Customer"
    },
    {
      "tag": "CreateField",
      "model": "Customer",
      "field": "id",
      "type": "Int",
      "arity": "Required"
    },
    {
      "tag": "CreateDirective",
      "location": {
        "path": {
          "tag": "Field",
          "model": "Customer",
          "field": "id"
        },
        "directive": "id"
      }
    },
    {
      "tag": "CreateDirective",
      "location": {
        "path": {
          "tag": "Field",
          "model": "Customer",
          "field": "id"
        },
        "directive": "default"
      }
    },
    {
      "tag": "CreateArgument",
      "location": {
        "tag": "Directive",
        "path": {
          "tag": "Field",
          "model": "Customer",
          "field": "id"
        },
        "directive": "default"
      },
      "argument": "",
      "value": "autoincrement()"
    },
    {
      "tag": "CreateField",
      "model": "Customer",
      "field": "name",
      "type": "String",
      "arity": "Optional"
    },
    {
      "tag": "CreateField",
      "model": "Customer",
      "field": "from_customer",
      "type": "Table",
      "arity": "List"
    },
    {
      "tag": "CreateDirective",
      "location": {
        "path": {
          "tag": "Field",
          "model": "Customer",
          "field": "from_customer"
        },
        "directive": "relation"
      }
    },
    {
      "tag": "CreateArgument",
      "location": {
        "tag": "Directive",
        "path": {
          "tag": "Field",
          "model": "Customer",
          "field": "from_customer"
        },
        "directive": "relation"
      },
      "argument": "",
      "value": "\"Table_customer_many\""
    },
    {
      "tag": "CreateArgument",
      "location": {
        "tag": "Directive",
        "path": {
          "tag": "Field",
          "model": "Customer",
          "field": "from_customer"
        },
        "directive": "relation"
      },
      "argument": "references",
      "value": "[id]"
    },
    {
      "tag": "CreateField",
      "model": "Table",
      "field": "seats",
      "type": "Int",
      "arity": "Optional"
    },
    {
      "tag": "CreateField",
      "model": "Table",
      "field": "customer",
      "type": "Customer",
      "arity": "List"
    },
    {
      "tag": "CreateDirective",
      "location": {
        "path": {
          "tag": "Field",
          "model": "Table",
          "field": "customer"
        },
        "directive": "relation"
      }
    },
    {
      "tag": "CreateArgument",
      "location": {
        "tag": "Directive",
        "path": {
          "tag": "Field",
          "model": "Table",
          "field": "customer"
        },
        "directive": "relation"
      },
      "argument": "",
      "value": "\"Table_customer_many\""
    },
    {
      "tag": "CreateArgument",
      "location": {
        "tag": "Directive",
        "path": {
          "tag": "Field",
          "model": "Table",
          "field": "customer"
        },
        "directive": "relation"
      },
      "argument": "references",
      "value": "[id]"
    }
  ]
}